{"cameraMode":{"drawMode":0,"name":"Shaded","section":"Shading Mode"},"sceneLighting":true,"audioPlay":false,"sceneViewState":{"m_AlwaysRefresh":false,"showFog":true,"showSkybox":true,"showFlares":true,"showImageEffects":true,"showParticleSystems":true,"showVisualEffectGraphs":true,"m_FxEnabled":true},"in2DMode":false,"pivot":{"x":0.8317685127258301,"y":-2.4283804893493654,"z":2.86134672164917},"rotation":{"x":0.14728544652462007,"y":0.314497172832489,"z":-0.04946369305253029,"w":0.936464250087738},"size":17.768024444580079,"orthographic":false}